/* Code */
import androidx.compose.runtime.*
import androidx.compose.foundation.layout.*
import androidx.compose.material3.Text
             
@Composable
fun Value(): String? {
    return "value: 0"
}

@Composable
fun Foo() {
    val value = Value() ?: return
    Column {
        Text(value)
    }
}

 /* Tree */ 
class TestKt {
    fun Foo$lambda$0 (ILandroidx/compose/runtime/Composer;I)Lkotlin/Unit; {
        Method (group=null)
        L0
        ALOAD 1
        ILOAD 0
        ICONST_1
        IOR
        INVOKESTATIC androidx/compose/runtime/RecomposeScopeImplKt.updateChangedFlags (I)I
        INVOKESTATIC TestKt.Foo (Landroidx/compose/runtime/Composer;I)V
        GETSTATIC kotlin/Unit.INSTANCE : Lkotlin/Unit;
        ARETURN
        L1
        }
    }
    
    fun Foo$lambda$2 (ILandroidx/compose/runtime/Composer;I)Lkotlin/Unit; {
        Method (group=null)
        L0
        ALOAD 1
        ILOAD 0
        ICONST_1
        IOR
        INVOKESTATIC androidx/compose/runtime/RecomposeScopeImplKt.updateChangedFlags (I)I
        INVOKESTATIC TestKt.Foo (Landroidx/compose/runtime/Composer;I)V
        GETSTATIC kotlin/Unit.INSTANCE : Lkotlin/Unit;
        ARETURN
        L1
        }
    }
    
    fun Foo (Landroidx/compose/runtime/Composer;I)V {
        Method (group=ComposeGroupKey(key=-607362160))
        L0
        LINENUMBER 11 L0
        ALOAD 0
            RestartGroup (group=ComposeGroupKey(key=-607362160))
            LDC -607362160
            INVOKEINTERFACE androidx/compose/runtime/Composer.startRestartGroup (I)Landroidx/compose/runtime/Composer; (itf)
            ASTORE 0
            ALOAD 0
            ILOAD 1
            IFEQ L1
            ICONST_1
            GOTO L2
            L1
            FRAME SAME1 androidx/compose/runtime/Composer
            ICONST_0
            L2
            FRAME FULL [androidx/compose/runtime/Composer I] [androidx/compose/runtime/Composer I]
            ILOAD 1
            ICONST_1
            IAND
            INVOKEINTERFACE androidx/compose/runtime/Composer.shouldExecute (ZI)Z (itf)
            IFEQ L3
            INVOKESTATIC androidx/compose/runtime/ComposerKt.isTraceInProgress ()Z
            IFEQ L4
            LDC -607362160
            ILOAD 1
            ICONST_M1
            LDC "Foo (Test.kt:10)"
            INVOKESTATIC androidx/compose/runtime/ComposerKt.traceEventStart (IIILjava/lang/String;)V
            L4
            LINENUMBER 12 L4
            FRAME SAME
            ALOAD 0
            ICONST_0
            INVOKESTATIC TestKt.Value (Landroidx/compose/runtime/Composer;I)Ljava/lang/String;
            DUP
            IFNONNULL L5
            POP
            INVOKESTATIC androidx/compose/runtime/ComposerKt.isTraceInProgress ()Z
            IFEQ L6
            INVOKESTATIC androidx/compose/runtime/ComposerKt.traceEventEnd ()V
            L6
            LINENUMBER 16 L6
            FRAME SAME
            ALOAD 0
            INVOKEINTERFACE androidx/compose/runtime/Composer.endRestartGroup ()Landroidx/compose/runtime/ScopeUpdateScope; (itf)
        Method (group=ComposeGroupKey(key=-607362160))
        DUP
        IFNULL L7
        ILOAD 1
        INVOKEDYNAMIC invoke(I)Lkotlin/jvm/functions/Function2; [
              // handle kind 0x6 : INVOKESTATIC
              java/lang/invoke/LambdaMetafactory.metafactory(Ljava/lang/invoke/MethodHandles$Lookup;Ljava/lang/String;Ljava/lang/invoke/MethodType;Ljava/lang/invoke/MethodType;Ljava/lang/invoke/MethodHandle;Ljava/lang/invoke/MethodType;)Ljava/lang/invoke/CallSite;
              // arguments:
              (Ljava/lang/Object;Ljava/lang/Object;)Ljava/lang/Object;, 
              // handle kind 0x6 : INVOKESTATIC
              TestKt.Foo$lambda$0(ILandroidx/compose/runtime/Composer;I)Lkotlin/Unit;, 
              (Landroidx/compose/runtime/Composer;Ljava/lang/Integer;)Lkotlin/Unit;
            ]
        INVOKEINTERFACE androidx/compose/runtime/ScopeUpdateScope.updateScope (Lkotlin/jvm/functions/Function2;)V (itf)
        GOTO L8
        L7
        FRAME SAME1 androidx/compose/runtime/ScopeUpdateScope
        POP
        L8
        LINENUMBER 12 L8
        FRAME SAME
        RETURN
            RestartGroup (group=ComposeGroupKey(key=-607362160))
            L5
            FRAME SAME1 java/lang/String
            ASTORE 2
            L9
            ALOAD 0
            ASTORE 6
            ICONST_0
            ISTORE 7
            L10
            LINENUMBER 13 L10
            NOP
            L11
            ICONST_0
            ISTORE 8
            L12
            ALOAD 6
            LDC 1341605231
            LDC "CC(Column)P(2,3,1)87@4443L61,88@4509L134:Column.kt#2w3rfo"
            L13
            LINENUMBER 17 L13
            INVOKESTATIC androidx/compose/runtime/ComposerKt.sourceInformationMarkerStart (Landroidx/compose/runtime/Composer;ILjava/lang/String;)V
            L14
            LINENUMBER 18 L14
            GETSTATIC androidx/compose/ui/Modifier.Companion : Landroidx/compose/ui/Modifier$Companion;
            CHECKCAST androidx/compose/ui/Modifier
            ASTORE 3
            L15
            LINENUMBER 19 L15
            GETSTATIC androidx/compose/foundation/layout/Arrangement.INSTANCE : Landroidx/compose/foundation/layout/Arrangement;
            INVOKEVIRTUAL androidx/compose/foundation/layout/Arrangement.getTop ()Landroidx/compose/foundation/layout/Arrangement$Vertical;
            ASTORE 4
            L16
            LINENUMBER 20 L16
            GETSTATIC androidx/compose/ui/Alignment.Companion : Landroidx/compose/ui/Alignment$Companion;
            INVOKEVIRTUAL androidx/compose/ui/Alignment$Companion.getStart ()Landroidx/compose/ui/Alignment$Horizontal;
            ASTORE 5
            L17
            LINENUMBER 23 L17
            ALOAD 4
            ALOAD 5
            ALOAD 6
            BIPUSH 14
            ILOAD 7
            ICONST_3
            ISHR
            IAND
            BIPUSH 112
            ILOAD 7
            ICONST_3
            ISHR
            IAND
            IOR
            INVOKESTATIC androidx/compose/foundation/layout/ColumnKt.columnMeasurePolicy (Landroidx/compose/foundation/layout/Arrangement$Vertical;Landroidx/compose/ui/Alignment$Horizontal;Landroidx/compose/runtime/Composer;I)Landroidx/compose/ui/layout/MeasurePolicy;
            ASTORE 9
            L18
            LINENUMBER 27 L18
            ALOAD 3
            ASTORE 10
            BIPUSH 112
            ILOAD 7
            ICONST_3
            ISHL
            IAND
            ISTORE 11
            L19
            LINENUMBER 24 L19
            NOP
            L20
            ICONST_0
            ISTORE 12
            L21
            ALOAD 6
            LDC -1159599143
            LDC "CC(Layout)P(!1,2)80@3267L27,83@3433L360:Layout.kt#80mrfh"
            L22
            LINENUMBER 28 L22
            INVOKESTATIC androidx/compose/runtime/ComposerKt.sourceInformationMarkerStart (Landroidx/compose/runtime/Composer;ILjava/lang/String;)V
            L23
            LINENUMBER 29 L23
            ALOAD 6
            ICONST_0
            INVOKESTATIC androidx/compose/runtime/ComposablesKt.getCurrentCompositeKeyHashCode (Landroidx/compose/runtime/Composer;I)J
            INVOKESTATIC java/lang/Long.hashCode (J)I
            ISTORE 13
            L24
            ALOAD 6
            L25
            LINENUMBER 30 L25
            INVOKEINTERFACE androidx/compose/runtime/Composer.getCurrentCompositionLocalMap ()Landroidx/compose/runtime/CompositionLocalMap; (itf)
            ASTORE 14
            L26
            ALOAD 6
            L27
            LINENUMBER 31 L27
            ALOAD 10
            INVOKESTATIC androidx/compose/ui/ComposedModifierKt.materializeModifier (Landroidx/compose/runtime/Composer;Landroidx/compose/ui/Modifier;)Landroidx/compose/ui/Modifier;
            ASTORE 15
            L28
            LINENUMBER 33 L28
            GETSTATIC androidx/compose/ui/node/ComposeUiNode.Companion : Landroidx/compose/ui/node/ComposeUiNode$Companion;
            INVOKEVIRTUAL androidx/compose/ui/node/ComposeUiNode$Companion.getConstructor ()Lkotlin/jvm/functions/Function0;
            ASTORE 16
            BIPUSH 6
            SIPUSH 896
            ILOAD 11
            BIPUSH 6
            ISHL
            IAND
            IOR
            ISTORE 17
            L29
            LINENUMBER 32 L29
            NOP
            L30
            ICONST_0
            ISTORE 18
            L31
            ALOAD 6
            LDC -553112988
            LDC "CC(ReusableComposeNode)N(factory,update,content)399@15590L9:Composables.kt#9igjgp"
            L32
            LINENUMBER 34 L32
            INVOKESTATIC androidx/compose/runtime/ComposerKt.sourceInformationMarkerStart (Landroidx/compose/runtime/Composer;ILjava/lang/String;)V
            L33
            LINENUMBER 35 L33
            ALOAD 6
            INVOKEINTERFACE androidx/compose/runtime/Composer.getApplier ()Landroidx/compose/runtime/Applier; (itf)
            INSTANCEOF androidx/compose/runtime/Applier
            IFNE L34
            INVOKESTATIC androidx/compose/runtime/ComposablesKt.invalidApplier ()V
            L34
            FRAME FULL [androidx/compose/runtime/Composer I java/lang/String androidx/compose/ui/Modifier androidx/compose/foundation/layout/Arrangement$Vertical androidx/compose/ui/Alignment$Horizontal androidx/compose/runtime/Composer I I androidx/compose/ui/layout/MeasurePolicy androidx/compose/ui/Modifier I I I androidx/compose/runtime/CompositionLocalMap androidx/compose/ui/Modifier kotlin/jvm/functions/Function0 I I] []
            ALOAD 6
            L35
            LINENUMBER 36 L35
            INVOKEINTERFACE androidx/compose/runtime/Composer.startReusableNode ()V (itf)
            L36
            LINENUMBER 37 L36
            ALOAD 6
            INVOKEINTERFACE androidx/compose/runtime/Composer.getInserting ()Z (itf)
            IFEQ L37
            ALOAD 6
            L38
            LINENUMBER 38 L38
            ALOAD 16
            INVOKEINTERFACE androidx/compose/runtime/Composer.createNode (Lkotlin/jvm/functions/Function0;)V (itf)
            GOTO L39
            L37
            FRAME SAME
            ALOAD 6
            L40
            LINENUMBER 40 L40
            INVOKEINTERFACE androidx/compose/runtime/Composer.useNode ()V (itf)
            L39
            LINENUMBER 42 L39
            FRAME SAME
            ALOAD 6
            INVOKESTATIC androidx/compose/runtime/Updater.constructor-impl (Landroidx/compose/runtime/Composer;)Landroidx/compose/runtime/Composer;
            ASTORE 19
            L41
            ICONST_0
            ISTORE 20
            L42
            LINENUMBER 43 L42
            ALOAD 19
            ALOAD 9
            GETSTATIC androidx/compose/ui/node/ComposeUiNode.Companion : Landroidx/compose/ui/node/ComposeUiNode$Companion;
            INVOKEVIRTUAL androidx/compose/ui/node/ComposeUiNode$Companion.getSetMeasurePolicy ()Lkotlin/jvm/functions/Function2;
            INVOKESTATIC androidx/compose/runtime/Updater.set-impl (Landroidx/compose/runtime/Composer;Ljava/lang/Object;Lkotlin/jvm/functions/Function2;)V
            L43
            LINENUMBER 44 L43
            ALOAD 19
            ALOAD 14
            GETSTATIC androidx/compose/ui/node/ComposeUiNode.Companion : Landroidx/compose/ui/node/ComposeUiNode$Companion;
            INVOKEVIRTUAL androidx/compose/ui/node/ComposeUiNode$Companion.getSetResolvedCompositionLocals ()Lkotlin/jvm/functions/Function2;
            INVOKESTATIC androidx/compose/runtime/Updater.set-impl (Landroidx/compose/runtime/Composer;Ljava/lang/Object;Lkotlin/jvm/functions/Function2;)V
            L44
            LINENUMBER 45 L44
            GETSTATIC androidx/compose/ui/node/ComposeUiNode.Companion : Landroidx/compose/ui/node/ComposeUiNode$Companion;
            INVOKEVIRTUAL androidx/compose/ui/node/ComposeUiNode$Companion.getSetCompositeKeyHash ()Lkotlin/jvm/functions/Function2;
            ASTORE 21
            L45
            ICONST_0
            ISTORE 22
            L46
            LINENUMBER 46 L46
            ALOAD 19
            ASTORE 23
            L47
            ICONST_0
            ISTORE 24
            L48
            LINENUMBER 47 L48
            ALOAD 23
            INVOKEINTERFACE androidx/compose/runtime/Composer.getInserting ()Z (itf)
            IFNE L49
            ALOAD 23
            INVOKEINTERFACE androidx/compose/runtime/Composer.rememberedValue ()Ljava/lang/Object; (itf)
            ILOAD 13
            INVOKESTATIC java/lang/Integer.valueOf (I)Ljava/lang/Integer;
            INVOKESTATIC kotlin/jvm/internal/Intrinsics.areEqual (Ljava/lang/Object;Ljava/lang/Object;)Z
            IFNE L50
            L49
            LINENUMBER 48 L49
            FRAME FULL [androidx/compose/runtime/Composer I java/lang/String androidx/compose/ui/Modifier androidx/compose/foundation/layout/Arrangement$Vertical androidx/compose/ui/Alignment$Horizontal androidx/compose/runtime/Composer I I androidx/compose/ui/layout/MeasurePolicy androidx/compose/ui/Modifier I I I androidx/compose/runtime/CompositionLocalMap androidx/compose/ui/Modifier kotlin/jvm/functions/Function0 I I androidx/compose/runtime/Composer I kotlin/jvm/functions/Function2 I androidx/compose/runtime/Composer I] []
            ALOAD 23
            ILOAD 13
            INVOKESTATIC java/lang/Integer.valueOf (I)Ljava/lang/Integer;
            INVOKEINTERFACE androidx/compose/runtime/Composer.updateRememberedValue (Ljava/lang/Object;)V (itf)
            L51
            LINENUMBER 49 L51
            ALOAD 19
            ILOAD 13
            INVOKESTATIC java/lang/Integer.valueOf (I)Ljava/lang/Integer;
            ALOAD 21
            INVOKEINTERFACE androidx/compose/runtime/Composer.apply (Ljava/lang/Object;Lkotlin/jvm/functions/Function2;)V (itf)
            L50
            LINENUMBER 51 L50
            FRAME SAME
            NOP
            L52
            LINENUMBER 46 L52
            NOP
            L53
            LINENUMBER 51 L53
            NOP
            L54
            LINENUMBER 52 L54
            ALOAD 19
            ALOAD 15
            GETSTATIC androidx/compose/ui/node/ComposeUiNode.Companion : Landroidx/compose/ui/node/ComposeUiNode$Companion;
            INVOKEVIRTUAL androidx/compose/ui/node/ComposeUiNode$Companion.getSetModifier ()Lkotlin/jvm/functions/Function2;
            INVOKESTATIC androidx/compose/runtime/Updater.set-impl (Landroidx/compose/runtime/Composer;Ljava/lang/Object;Lkotlin/jvm/functions/Function2;)V
            L55
            LINENUMBER 53 L55
            NOP
            L56
            LINENUMBER 42 L56
            NOP
            L57
            LINENUMBER 54 L57
            ALOAD 6
            BIPUSH 14
            ILOAD 17
            BIPUSH 6
            ISHR
            IAND
            ISTORE 25
            ASTORE 26
            L58
            ICONST_0
            ISTORE 27
            L59
            ALOAD 26
            LDC 2093002350
            LDC "C89@4557L9:Column.kt#2w3rfo"
            L60
            LINENUMBER 25 L60
            INVOKESTATIC androidx/compose/runtime/ComposerKt.sourceInformationMarkerStart (Landroidx/compose/runtime/Composer;ILjava/lang/String;)V
            GETSTATIC androidx/compose/foundation/layout/ColumnScopeInstance.INSTANCE : Landroidx/compose/foundation/layout/ColumnScopeInstance;
            ALOAD 26
            BIPUSH 6
            BIPUSH 112
            ILOAD 7
            BIPUSH 6
            ISHR
            IAND
            IOR
            ISTORE 28
            ASTORE 29
            CHECKCAST androidx/compose/foundation/layout/ColumnScope
            ASTORE 30
            L61
            ICONST_0
            ISTORE 31
            L62
            LINENUMBER 14 L62
            ALOAD 2
            ACONST_NULL
            LCONST_0
            LCONST_0
            ACONST_NULL
            ACONST_NULL
            ACONST_NULL
            LCONST_0
            ACONST_NULL
            ACONST_NULL
            LCONST_0
            ICONST_0
            ICONST_0
            ICONST_0
            ICONST_0
            ACONST_NULL
            ACONST_NULL
            ALOAD 29
            ICONST_0
            ICONST_0
            LDC 131070
            INVOKESTATIC androidx/compose/material3/TextKt.Text--4IGK_g (Ljava/lang/String;Landroidx/compose/ui/Modifier;JJLandroidx/compose/ui/text/font/FontStyle;Landroidx/compose/ui/text/font/FontWeight;Landroidx/compose/ui/text/font/FontFamily;JLandroidx/compose/ui/text/style/TextDecoration;Landroidx/compose/ui/text/style/TextAlign;JIZIILkotlin/jvm/functions/Function1;Landroidx/compose/ui/text/TextStyle;Landroidx/compose/runtime/Composer;III)V
            L63
            LINENUMBER 15 L63
            NOP
            L64
            LINENUMBER 25 L64
            ALOAD 26
            INVOKESTATIC androidx/compose/runtime/ComposerKt.sourceInformationMarkerEnd (Landroidx/compose/runtime/Composer;)V
            L65
            LINENUMBER 54 L65
            ALOAD 6
            L66
            LINENUMBER 55 L66
            INVOKEINTERFACE androidx/compose/runtime/Composer.endNode ()V (itf)
            ALOAD 6
            L67
            LINENUMBER 34 L67
            INVOKESTATIC androidx/compose/runtime/ComposerKt.sourceInformationMarkerEnd (Landroidx/compose/runtime/Composer;)V
            L68
            LINENUMBER 56 L68
            NOP
            L69
            ALOAD 6
            L70
            LINENUMBER 28 L70
            INVOKESTATIC androidx/compose/runtime/ComposerKt.sourceInformationMarkerEnd (Landroidx/compose/runtime/Composer;)V
            L71
            LINENUMBER 57 L71
            NOP
            L72
            ALOAD 6
            L73
            LINENUMBER 17 L73
            INVOKESTATIC androidx/compose/runtime/ComposerKt.sourceInformationMarkerEnd (Landroidx/compose/runtime/Composer;)V
            L74
            LINENUMBER 58 L74
            NOP
            L75
            INVOKESTATIC androidx/compose/runtime/ComposerKt.isTraceInProgress ()Z
            IFEQ L76
            INVOKESTATIC androidx/compose/runtime/ComposerKt.traceEventEnd ()V
            L77
            GOTO L76
            L3
            LINENUMBER 10 L3
            FRAME FULL [androidx/compose/runtime/Composer I] []
            ALOAD 0
            INVOKEINTERFACE androidx/compose/runtime/Composer.skipToGroupEnd ()V (itf)
            L76
            LINENUMBER 16 L76
            FRAME SAME
            ALOAD 0
            INVOKEINTERFACE androidx/compose/runtime/Composer.endRestartGroup ()Landroidx/compose/runtime/ScopeUpdateScope; (itf)
        Method (group=ComposeGroupKey(key=-607362160))
        DUP
        IFNULL L78
        ILOAD 1
        INVOKEDYNAMIC invoke(I)Lkotlin/jvm/functions/Function2; [
              // handle kind 0x6 : INVOKESTATIC
              java/lang/invoke/LambdaMetafactory.metafactory(Ljava/lang/invoke/MethodHandles$Lookup;Ljava/lang/String;Ljava/lang/invoke/MethodType;Ljava/lang/invoke/MethodType;Ljava/lang/invoke/MethodHandle;Ljava/lang/invoke/MethodType;)Ljava/lang/invoke/CallSite;
              // arguments:
              (Ljava/lang/Object;Ljava/lang/Object;)Ljava/lang/Object;, 
              // handle kind 0x6 : INVOKESTATIC
              TestKt.Foo$lambda$2(ILandroidx/compose/runtime/Composer;I)Lkotlin/Unit;, 
              (Landroidx/compose/runtime/Composer;Ljava/lang/Integer;)Lkotlin/Unit;
            ]
        INVOKEINTERFACE androidx/compose/runtime/ScopeUpdateScope.updateScope (Lkotlin/jvm/functions/Function2;)V (itf)
        GOTO L79
        L78
        FRAME SAME1 androidx/compose/runtime/ScopeUpdateScope
        POP
        L79
        FRAME SAME
        RETURN
        L80
        }
    }
    
    fun Value (Landroidx/compose/runtime/Composer;I)Ljava/lang/String; {
        Method (group=ComposeGroupKey(key=-1250970360))
        L0
        INVOKESTATIC androidx/compose/runtime/ComposerKt.isTraceInProgress ()Z
        IFEQ L1
        LDC -1250970360
        ILOAD 1
        ICONST_M1
        LDC "Value (Test.kt:5)"
        INVOKESTATIC androidx/compose/runtime/ComposerKt.traceEventStart (IIILjava/lang/String;)V
        L1
        FRAME SAME
        INVOKESTATIC androidx/compose/runtime/ComposerKt.isTraceInProgress ()Z
        IFEQ L2
        INVOKESTATIC androidx/compose/runtime/ComposerKt.traceEventEnd ()V
        L2
        FRAME SAME
        LDC "value: 0"
        L3
        LINENUMBER 7 L3
        ARETURN
        L4
        }
    }
}